klvm_rs-0.16.1.dist-info/METADATA
klvm_rs-0.16.1.dist-info/WHEEL
klvm_rs.libs/libcrypto-bdaed0ea.so.1.1
klvm_rs/__init__.py
klvm_rs/at.py
klvm_rs/casts.py
klvm_rs/chik_dialect.py
klvm_rs/curry_and_treehash.py
klvm_rs/de.py
klvm_rs/eval_error.py
klvm_rs/klvm_rs.abi3.so
klvm_rs/klvm_rs.pyi
klvm_rs/klvm_storage.py
klvm_rs/klvm_tree.py
klvm_rs/program.py
klvm_rs/py.typed
klvm_rs/replace.py
klvm_rs/ser.py
klvm_rs/tree_hash.py
klvm_rs-0.16.1.dist-info/RECORD
