Metadata-Version: 2.4
Name: klvm_rs
Version: 0.16.1
Summary: Implementation of `klvm` for Chik Network's cryptocurrency
Home-Page: https://github.com/Chik-Network/klvm_rs/
Author: Richard Kiss <him@richardkiss.com>
Author-email: Richard Kiss <him@richardkiss.com>
License: Apache-2.0
Project-URL: Source Code, https://github.com/Chik-Network/klvm_rs/
